cc_cleaner/__init__.py
cc_cleaner/__main__.py
cc_cleaner/cli.py
cc_cleaner/py.typed
cc_cleaner/cleaners/__init__.py
cc_cleaner/cleaners/browser_cache.py
cc_cleaner/cleaners/browser_tools.py
cc_cleaner/cleaners/bun.py
cc_cleaner/cleaners/cargo.py
cc_cleaner/cleaners/claude.py
cc_cleaner/cleaners/cocoapods.py
cc_cleaner/cleaners/docker.py
cc_cleaner/cleaners/go.py
cc_cleaner/cleaners/gradle.py
cc_cleaner/cleaners/homebrew.py
cc_cleaner/cleaners/huggingface.py
cc_cleaner/cleaners/npm.py
cc_cleaner/cleaners/nvm.py
cc_cleaner/cleaners/ollama.py
cc_cleaner/cleaners/pip.py
cc_cleaner/cleaners/playwright.py
cc_cleaner/cleaners/pnpm.py
cc_cleaner/cleaners/pytorch.py
cc_cleaner/cleaners/uv.py
cc_cleaner/cleaners/virtualenv.py
cc_cleaner/cleaners/whisper.py
cc_cleaner/cleaners/yarn.py
cc_cleaner/core/__init__.py
cc_cleaner/core/base.py
cc_cleaner/core/cache.py
cc_cleaner/core/executor.py
cc_cleaner/core/registry.py
cc_cleaner/core/scanner.py
cc_cleaner/core/security.py
cc_cleaner/core/version.py
cc_cleaner/ui/__init__.py
cc_cleaner/ui/console.py
cc_cleaner/ui/interactive.py
cc_cleaner-0.4.1.dist-info/METADATA
cc_cleaner-0.4.1.dist-info/WHEEL
cc_cleaner-0.4.1.dist-info/entry_points.txt
cc_cleaner-0.4.1.dist-info/licenses/LICENSE
cc_cleaner-0.4.1.dist-info/RECORD
