Metadata-Version: 2.4
Name: cc-cleaner
Version: 0.4.1
Summary: The cache cleaner for the AI Coding era. Clean up Claude Code, Cursor, npm, pip, cargo caches and more.
Project-URL: Homepage, https://github.com/elexingyu/cc-cleaner
Project-URL: Repository, https://github.com/elexingyu/cc-cleaner
Project-URL: Issues, https://github.com/elexingyu/cc-cleaner/issues
Author-email: elexingyu <elexingyu@gmail.com>
License-Expression: MIT
License-File: LICENSE
Keywords: ai-coding,cache,cargo,claude-code,cleaner,cli,copilot,cursor,developer-tools,disk-space,docker,npm,pip
Classifier: Development Status :: 4 - Beta
Classifier: Environment :: Console
Classifier: Intended Audience :: Developers
Classifier: License :: OSI Approved :: MIT License
Classifier: Operating System :: MacOS
Classifier: Operating System :: POSIX :: Linux
Classifier: Programming Language :: Python :: 3
Classifier: Programming Language :: Python :: 3.10
Classifier: Programming Language :: Python :: 3.11
Classifier: Programming Language :: Python :: 3.12
Classifier: Programming Language :: Python :: 3.13
Classifier: Topic :: System :: Systems Administration
Classifier: Topic :: Utilities
Classifier: Typing :: Typed
Requires-Python: >=3.10
Requires-Dist: rich>=13.0.0
Requires-Dist: typer>=0.9.0
